finawell_funciona_oferta_incrivel_leve_4_pague_1_so_hoje/__init__.py
finawell_funciona_oferta_incrivel_leve_4_pague_1_so_hoje-0.0.1.dist-info/LICENSE
finawell_funciona_oferta_incrivel_leve_4_pague_1_so_hoje-0.0.1.dist-info/METADATA
finawell_funciona_oferta_incrivel_leve_4_pague_1_so_hoje-0.0.1.dist-info/WHEEL
finawell_funciona_oferta_incrivel_leve_4_pague_1_so_hoje-0.0.1.dist-info/top_level.txt
finawell_funciona_oferta_incrivel_leve_4_pague_1_so_hoje-0.0.1.dist-info/RECORD
