Metadata-Version: 2.1
Name: finawell-funciona-oferta-incrivel-leve-4-pague-1-so-hoje
Version: 0.0.1
Summary: Finawell funciona? Promoção Hoje: Leve 4 potes pelo preço de 1! Garantia de 90 dias! Veja fotos do Finalwell Antes e Depois. Confira Já, só Hoje!
Home-page: https://github.com/pypa/sampleproject
Author: Example Author
Author-email: author@example.com
License: UNKNOWN
Project-URL: Bug Tracker, https://github.com/pypa/sampleproject/issues
Platform: UNKNOWN
Classifier: Programming Language :: Python :: 3
Classifier: License :: OSI Approved :: MIT License
Classifier: Operating System :: OS Independent
Requires-Python: >=3.6
License-File: LICENSE
